[
  {
    "nama": "ABBAS",
    "kelas": "IX - 1",
    "nisn": "0105002333",
    "keterangan": "LULUS"
  },
  {
    "nama": "AHMAD FAHRIZAL",
    "kelas": "IX - 1",
    "nisn": 3102589325,
    "keterangan": "LULUS"
  },
  {
    "nama": "ALDIANSYAH ARAFAT",
    "kelas": "IX - 1",
    "nisn": "0102604009",
    "keterangan": "LULUS"
  },
  {
    "nama": "ASHIKA SAFA SHAKILA CHANIAGO",
    "kelas": "IX - 1",
    "nisn": "0117139043",
    "keterangan": "LULUS"
  },
  {
    "nama": "AULIA KHAIRUNISA",
    "kelas": "IX - 1",
    "nisn": "0107378097",
    "keterangan": "LULUS"
  },
  {
    "nama": "BIMA ROBBY AL FALLAH",
    "kelas": "IX - 1",
    "nisn": "0109241956",
    "keterangan": "LULUS"
  },
  {
    "nama": "DEBY PUSPITA",
    "kelas": "IX - 1",
    "nisn": "0105812117",
    "keterangan": "LULUS"
  },
  {
    "nama": "ENDA AZALISA",
    "kelas": "IX - 1",
    "nisn": "0093601255",
    "keterangan": "LULUS"
  },
  {
    "nama": "FERRY ROSLANA",
    "kelas": "IX - 1",
    "nisn": "0094346189",
    "keterangan": "LULUS"
  },
  {
    "nama": "IBRAHIM OMAR",
    "kelas": "IX - 1",
    "nisn": 3104806043,
    "keterangan": "LULUS"
  },
  {
    "nama": "INDAH SYAKEYLA",
    "kelas": "IX - 1",
    "nisn": "0118723602",
    "keterangan": "LULUS"
  },
  {
    "nama": "M ADIT SYAHPUTRA RITONGA",
    "kelas": "IX - 1",
    "nisn": "0108082227",
    "keterangan": "LULUS"
  },
  {
    "nama": "MEGA SOFIAH",
    "kelas": "IX - 1",
    "nisn": "0103198596",
    "keterangan": "LULUS"
  },
  {
    "nama": "MIFTAHUR RIZKI YURI",
    "kelas": "IX - 1",
    "nisn": 3091362054,
    "keterangan": "LULUS"
  },
  {
    "nama": "MUHAMMAD RADITIYA PRANATA",
    "kelas": "IX - 1",
    "nisn": "0091551643",
    "keterangan": "LULUS"
  },
  {
    "nama": "MUHAMMAD RAFLI RAMADHANA",
    "kelas": "IX - 1",
    "nisn": "0106810968",
    "keterangan": "LULUS"
  },
  {
    "nama": "MUSTHOFA DZAKI",
    "kelas": "IX - 1",
    "nisn": "0118556261",
    "keterangan": "LULUS"
  },
  {
    "nama": "MUTIA KASIH",
    "kelas": "IX - 1",
    "nisn": "0104815357",
    "keterangan": "LULUS"
  },
  {
    "nama": "NADHIRA AQILA NINGRUM",
    "kelas": "IX - 1",
    "nisn": 3100593118,
    "keterangan": "LULUS"
  },
  {
    "nama": "NAZWA AMALIA PUTRI",
    "kelas": "IX - 1",
    "nisn": 3090704894,
    "keterangan": "LULUS"
  },
  {
    "nama": "PUSPA NATASYA",
    "kelas": "IX - 1",
    "nisn": "0099269992",
    "keterangan": "LULUS"
  },
  {
    "nama": "RAFFI ANANDA",
    "kelas": "IX - 1",
    "nisn": "0088636522",
    "keterangan": "LULUS"
  },
  {
    "nama": "REFALIN KHAIRUNISA AHMADI",
    "kelas": "IX - 1",
    "nisn": "0094969883",
    "keterangan": "LULUS"
  },
  {
    "nama": "SHAFA AZZARA",
    "kelas": "IX - 1",
    "nisn": "0101649083",
    "keterangan": "LULUS"
  },
  {
    "nama": "SOFYAN REYFANDI AULIA RAMBE",
    "kelas": "IX - 1",
    "nisn": "0102232399",
    "keterangan": "LULUS"
  },
  {
    "nama": "SYAVA BILBINA",
    "kelas": "IX - 1",
    "nisn": 3092106556,
    "keterangan": "LULUS"
  },
  {
    "nama": "TENGKU MUHAMMAD NOUFAL HAFIDZ",
    "kelas": "IX - 1",
    "nisn": "0104997718",
    "keterangan": "LULUS"
  },
  {
    "nama": "UMMI HANIPA LUBIS",
    "kelas": "IX - 1",
    "nisn": "0108711487",
    "keterangan": "LULUS"
  },
  {
    "nama": "VANIA CALLISTA SUWANDI",
    "kelas": "IX - 1",
    "nisn": 3102010940,
    "keterangan": "LULUS"
  },
  {
    "nama": "ZAKA MORINO KHADAFI SIMANULLANG",
    "kelas": "IX - 1",
    "nisn": 3102643952,
    "keterangan": "LULUS"
  },
  {
    "nama": "ZUHRA SHAKILA",
    "kelas": "IX - 1",
    "nisn": "0105373194",
    "keterangan": "LULUS"
  },
  {
    "nama": "ADAM AS SHAKA",
    "kelas": "IX - 2",
    "nisn": "0119898621",
    "keterangan": "LULUS"
  },
  {
    "nama": "ALFA DIANDRA",
    "kelas": "IX - 2",
    "nisn": "0107899417",
    "keterangan": "LULUS"
  },
  {
    "nama": "ANGGRAINI TARIGAN",
    "kelas": "IX - 2",
    "nisn": "0106398870",
    "keterangan": "LULUS"
  },
  {
    "nama": "ASY SYIFA FEBYOLA QUEEN",
    "kelas": "IX - 2",
    "nisn": "0111808499",
    "keterangan": "LULUS"
  },
  {
    "nama": "AYU NING TIAS",
    "kelas": "IX - 2",
    "nisn": "0109130436",
    "keterangan": "LULUS"
  },
  {
    "nama": "AZZAHRA RISFA",
    "kelas": "IX - 2",
    "nisn": "0105503115",
    "keterangan": "LULUS"
  },
  {
    "nama": "BIMO HABIB SUKANA",
    "kelas": "IX - 2",
    "nisn": "0093418566",
    "keterangan": "LULUS"
  },
  {
    "nama": "CAHAYA RAHMADHANI LUBIS",
    "kelas": "IX - 2",
    "nisn": "0103593574",
    "keterangan": "LULUS"
  },
  {
    "nama": "DELA FITRI ANINGSIH",
    "kelas": "IX - 2",
    "nisn": "0095413981",
    "keterangan": "LULUS"
  },
  {
    "nama": "DIMAZ ANDREAN DEPARI",
    "kelas": "IX - 2",
    "nisn": 3107018634,
    "keterangan": "LULUS"
  },
  {
    "nama": "DJUS SAFAATUL AULIA TANJUNG",
    "kelas": "IX - 2",
    "nisn": "0104444850",
    "keterangan": "LULUS"
  },
  {
    "nama": "FAHZLAH RANDINI",
    "kelas": "IX - 2",
    "nisn": "0091859988",
    "keterangan": "LULUS"
  },
  {
    "nama": "FIRZA LUCKY DWIYANSYAH",
    "kelas": "IX - 2",
    "nisn": "0103921857",
    "keterangan": "LULUS"
  },
  {
    "nama": "IBNU MAULANA",
    "kelas": "IX - 2",
    "nisn": "0104099919",
    "keterangan": "LULUS"
  },
  {
    "nama": "JASMINE KIRANIA AZ-ZAHRA",
    "kelas": "IX - 2",
    "nisn": "0107906738",
    "keterangan": "LULUS"
  },
  {
    "nama": "M ALDHY ALFAROZI",
    "kelas": "IX - 2",
    "nisn": "0102615062",
    "keterangan": "LULUS"
  },
  {
    "nama": "MAULANA SIDIQ",
    "kelas": "IX - 2",
    "nisn": "0101233133",
    "keterangan": "LULUS"
  },
  {
    "nama": "MEISYA AMANDA PUTRI",
    "kelas": "IX - 2",
    "nisn": 3102112719,
    "keterangan": "LULUS"
  },
  {
    "nama": "MOHAMMAD YUSUF EFENDI",
    "kelas": "IX - 2",
    "nisn": 3096430015,
    "keterangan": "LULUS"
  },
  {
    "nama": "MUHAMMAD DIMAS PRADITTIA",
    "kelas": "IX - 2",
    "nisn": "0105959082",
    "keterangan": "LULUS"
  },
  {
    "nama": "MUHAMMAD RAJA IMAN NUR HAKIMI",
    "kelas": "IX - 2",
    "nisn": "0104373437",
    "keterangan": "LULUS"
  },
  {
    "nama": "MUHAMMAD ZAIDAN WIJAYA",
    "kelas": "IX - 2",
    "nisn": "0101960381",
    "keterangan": "LULUS"
  },
  {
    "nama": "NADILA DEFANI",
    "kelas": "IX - 2",
    "nisn": "0101709474",
    "keterangan": "LULUS"
  },
  {
    "nama": "NAZWA APRILIANA BR.HARAHAP",
    "kelas": "IX - 2",
    "nisn": "0106440650",
    "keterangan": "LULUS"
  },
  {
    "nama": "PUTRI NABILA HAFSAH SINAGA",
    "kelas": "IX - 2",
    "nisn": "0108849410",
    "keterangan": "LULUS"
  },
  {
    "nama": "RAJA KIRANA",
    "kelas": "IX - 2",
    "nisn": "0097614017",
    "keterangan": "LULUS"
  },
  {
    "nama": "RICKY RAMADHAN LUBIS",
    "kelas": "IX - 2",
    "nisn": "0103219442",
    "keterangan": "LULUS"
  },
  {
    "nama": "RIRIN KHAIRUNNISA SYAHFITRI",
    "kelas": "IX - 2",
    "nisn": 3104286824,
    "keterangan": "LULUS"
  },
  {
    "nama": "SAKINA YUSMI",
    "kelas": "IX - 2",
    "nisn": "0106661097",
    "keterangan": "LULUS"
  },
  {
    "nama": "SHAFA NUR HAFIZA",
    "kelas": "IX - 2",
    "nisn": 3103869330,
    "keterangan": "LULUS"
  },
  {
    "nama": "VEGA NABILA",
    "kelas": "IX - 2",
    "nisn": "0107926835",
    "keterangan": "LULUS"
  },
  {
    "nama": "ZYGA REZY ADICKA",
    "kelas": "IX - 2",
    "nisn": "0101937930",
    "keterangan": "LULUS"
  },
  {
    "nama": "ADHEO DWI ZAKARIA",
    "kelas": "IX - 3",
    "nisn": "0104583036",
    "keterangan": "LULUS"
  },
  {
    "nama": "ALIF AL MISQY NUGRAHA",
    "kelas": "IX - 3",
    "nisn": "0107551380",
    "keterangan": "LULUS"
  },
  {
    "nama": "ANINDYA NAYLA ARKANNA",
    "kelas": "IX - 3",
    "nisn": "0109235727",
    "keterangan": "LULUS"
  },
  {
    "nama": "ASYFA AULIA",
    "kelas": "IX - 3",
    "nisn": "0106956197",
    "keterangan": "LULUS"
  },
  {
    "nama": "AYU REGINA PUTRI",
    "kelas": "IX - 3",
    "nisn": "0101523258",
    "keterangan": "LULUS"
  },
  {
    "nama": "AZZAH THABSYAHIRAH NASUTION",
    "kelas": "IX - 3",
    "nisn": "0101399047",
    "keterangan": "LULUS"
  },
  {
    "nama": "BINTANG MUDA RANGKUTI",
    "kelas": "IX - 3",
    "nisn": "0107608417",
    "keterangan": "LULUS"
  },
  {
    "nama": "DESWITA MALFA AFIZAH",
    "kelas": "IX - 3",
    "nisn": "0097018407",
    "keterangan": "LULUS"
  },
  {
    "nama": "DIKA PRASETYO",
    "kelas": "IX - 3",
    "nisn": 3095831026,
    "keterangan": "LULUS"
  },
  {
    "nama": "DINDA ZAHIRA",
    "kelas": "IX - 3",
    "nisn": "0093970246",
    "keterangan": "LULUS"
  },
  {
    "nama": "FADLI KESUMA",
    "kelas": "IX - 3",
    "nisn": "0084784934",
    "keterangan": "LULUS"
  },
  {
    "nama": "GALANG ARYA SIREGAR",
    "kelas": "IX - 3",
    "nisn": "0103370369",
    "keterangan": "LULUS"
  },
  {
    "nama": "INAYAH SAFIRA HASIBUAN",
    "kelas": "IX - 3",
    "nisn": "0104818980",
    "keterangan": "LULUS"
  },
  {
    "nama": "JAVINA ARDIFTA",
    "kelas": "IX - 3",
    "nisn": 3103979366,
    "keterangan": "LULUS"
  },
  {
    "nama": "KESHIA AUSHEVA",
    "kelas": "IX - 3",
    "nisn": 3109496074,
    "keterangan": "LULUS"
  },
  {
    "nama": "M IRFAN RAMADHAN",
    "kelas": "IX - 3",
    "nisn": "0109755961",
    "keterangan": "LULUS"
  },
  {
    "nama": "MELISA AMANDA",
    "kelas": "IX - 3",
    "nisn": "0099443323",
    "keterangan": "LULUS"
  },
  {
    "nama": "MHD FADIL",
    "kelas": "IX - 3",
    "nisn": "0109811276",
    "keterangan": "LULUS"
  },
  {
    "nama": "MUKTAR ARIF",
    "kelas": "IX - 3",
    "nisn": "0098256663",
    "keterangan": "LULUS"
  },
  {
    "nama": "NABILA RANGKUTI",
    "kelas": "IX - 3",
    "nisn": "0087973058",
    "keterangan": "LULUS"
  },
  {
    "nama": "NAIRA JULIANDA",
    "kelas": "IX - 3",
    "nisn": "0105803320",
    "keterangan": "LULUS"
  },
  {
    "nama": "NAZWA PERTIWI",
    "kelas": "IX - 3",
    "nisn": "0091345787",
    "keterangan": "LULUS"
  },
  {
    "nama": "NURUL ADINDA",
    "kelas": "IX - 3",
    "nisn": "0109610279",
    "keterangan": "LULUS"
  },
  {
    "nama": "RAFA ALFARIZI",
    "kelas": "IX - 3",
    "nisn": 3107470897,
    "keterangan": "LULUS"
  },
  {
    "nama": "RAYHAN AHMAD ASSHIDIQ SIKUMBANG",
    "kelas": "IX - 3",
    "nisn": "0103914773",
    "keterangan": "LULUS"
  },
  {
    "nama": "RAYSHA SAFANA AZARIA",
    "kelas": "IX - 3",
    "nisn": "0101778041",
    "keterangan": "LULUS"
  },
  {
    "nama": "RISKA AULIA HASIBUAN",
    "kelas": "IX - 3",
    "nisn": "0109484204",
    "keterangan": "LULUS"
  },
  {
    "nama": "SITI JUWITA",
    "kelas": "IX - 3",
    "nisn": "0102216544",
    "keterangan": "LULUS"
  },
  {
    "nama": "TEGAR HAMONANGAN PANJAITAN",
    "kelas": "IX - 3",
    "nisn": "0104070752",
    "keterangan": "LULUS"
  },
  {
    "nama": "VENI",
    "kelas": "IX - 3",
    "nisn": "0108027260",
    "keterangan": "LULUS"
  },
  {
    "nama": "ADJIE BAYHAQI MOENAF",
    "kelas": "IX - 4",
    "nisn": "0093304878",
    "keterangan": "LULUS"
  },
  {
    "nama": "AQILA DAWIYAH",
    "kelas": "IX - 4",
    "nisn": "0096400901",
    "keterangan": "LULUS"
  },
  {
    "nama": "ASYIFA AZRA SALSABILA",
    "kelas": "IX - 4",
    "nisn": "0106121462",
    "keterangan": "LULUS"
  },
  {
    "nama": "CUT NADIN AL-HUSNA",
    "kelas": "IX - 4",
    "nisn": "0083442483",
    "keterangan": "LULUS"
  },
  {
    "nama": "DAENG SYAWAL AL AKBAR",
    "kelas": "IX - 4",
    "nisn": "0094497214",
    "keterangan": "LULUS"
  },
  {
    "nama": "FAHRI ALFIANSYAH",
    "kelas": "IX - 4",
    "nisn": "0102798071",
    "keterangan": "LULUS"
  },
  {
    "nama": "FAIZ AL BANI",
    "kelas": "IX - 4",
    "nisn": "0106893332",
    "keterangan": "LULUS"
  },
  {
    "nama": "FAUZAN ZARKAWI ANHAR",
    "kelas": "IX - 4",
    "nisn": "0095028671",
    "keterangan": "LULUS"
  },
  {
    "nama": "HAFIZAH FADILLAH SARAGIH",
    "kelas": "IX - 4",
    "nisn": "0106120506",
    "keterangan": "LULUS"
  },
  {
    "nama": "IRFAN NURUDDIN",
    "kelas": "IX - 4",
    "nisn": "0114789746",
    "keterangan": "LULUS"
  },
  {
    "nama": "M REZA SAUFIE",
    "kelas": "IX - 4",
    "nisn": "0118111543",
    "keterangan": "LULUS"
  },
  {
    "nama": "M RILLY TOTI",
    "kelas": "IX - 4",
    "nisn": 3106560954,
    "keterangan": "LULUS"
  },
  {
    "nama": "MAYDIRA MUSTIKA ARAFAH",
    "kelas": "IX - 4",
    "nisn": 3101336955,
    "keterangan": "LULUS"
  },
  {
    "nama": "MHD. FAHRIANSYAH",
    "kelas": "IX - 4",
    "nisn": "0099353083",
    "keterangan": "LULUS"
  },
  {
    "nama": "MOZA KIRANA SIREGAR",
    "kelas": "IX - 4",
    "nisn": "0098621897",
    "keterangan": "LULUS"
  },
  {
    "nama": "MUHAMMAD ARYASYAH",
    "kelas": "IX - 4",
    "nisn": "0101755325",
    "keterangan": "LULUS"
  },
  {
    "nama": "MUHAMMAD FADHLI AZHMI",
    "kelas": "IX - 4",
    "nisn": "0109891540",
    "keterangan": "LULUS"
  },
  {
    "nama": "MUSTAKIM HABIB",
    "kelas": "IX - 4",
    "nisn": "0094151426",
    "keterangan": "LULUS"
  },
  {
    "nama": "NABILLA AMELIA",
    "kelas": "IX - 4",
    "nisn": "0108656677",
    "keterangan": "LULUS"
  },
  {
    "nama": "NAJMA 'ALYA BR SIANTURI",
    "kelas": "IX - 4",
    "nisn": "0105940518",
    "keterangan": "LULUS"
  },
  {
    "nama": "NOVA ELI ERMAWATI SIREGAR",
    "kelas": "IX - 4",
    "nisn": "0093561694",
    "keterangan": "LULUS"
  },
  {
    "nama": "NURATIFA ZAHRA",
    "kelas": "IX - 4",
    "nisn": "0108363527",
    "keterangan": "LULUS"
  },
  {
    "nama": "PRISILIA PUTRI",
    "kelas": "IX - 4",
    "nisn": "0106490566",
    "keterangan": "LULUS"
  },
  {
    "nama": "PUTRI SUCI RAMADHANI",
    "kelas": "IX - 4",
    "nisn": "0102091611",
    "keterangan": "LULUS"
  },
  {
    "nama": "REZA PRATAMA",
    "kelas": "IX - 4",
    "nisn": "0094029543",
    "keterangan": "LULUS"
  },
  {
    "nama": "RIJAL SEPTIANSYAH",
    "kelas": "IX - 4",
    "nisn": 3102239218,
    "keterangan": "LULUS"
  },
  {
    "nama": "ROSIA SITEPU",
    "kelas": "IX - 4",
    "nisn": "0105973344",
    "keterangan": "LULUS"
  },
  {
    "nama": "SAHARA",
    "kelas": "IX - 4",
    "nisn": "0093050023",
    "keterangan": "LULUS"
  },
  {
    "nama": "SYAFRIDHA MULYANA",
    "kelas": "IX - 4",
    "nisn": "0118635560",
    "keterangan": "LULUS"
  },
  {
    "nama": "TENGKU KHALIQ REYZAN PERDANA",
    "kelas": "IX - 4",
    "nisn": "0106987479",
    "keterangan": "LULUS"
  },
  {
    "nama": "YASMIN PUTRI DERMAWAN",
    "kelas": "IX - 4",
    "nisn": "0109823166",
    "keterangan": "LULUS"
  },
  {
    "nama": "ADELINA MARGARETA L.TOBING",
    "kelas": "IX - 5",
    "nisn": "0126610221",
    "keterangan": "LULUS"
  },
  {
    "nama": "AGUNG SETIAWAN",
    "kelas": "IX - 5",
    "nisn": "0106209707",
    "keterangan": "LULUS"
  },
  {
    "nama": "ANDRA TIMOTHY SINAGA",
    "kelas": "IX - 5",
    "nisn": "0118561992",
    "keterangan": "LULUS"
  },
  {
    "nama": "APRIANSYAH ALAM HRP",
    "kelas": "IX - 5",
    "nisn": "0107062918",
    "keterangan": "LULUS"
  },
  {
    "nama": "CHIKA SIANIPAR",
    "kelas": "IX - 5",
    "nisn": "0106384494",
    "keterangan": "LULUS"
  },
  {
    "nama": "DAFA ANDIKA PRATAMA",
    "kelas": "IX - 5",
    "nisn": "0094525541",
    "keterangan": "LULUS"
  },
  {
    "nama": "DHEA AMANDA",
    "kelas": "IX - 5",
    "nisn": "0105768418",
    "keterangan": "LULUS"
  },
  {
    "nama": "EVITA HERLYANA ROSE SINABUTAR",
    "kelas": "IX - 5",
    "nisn": "0103431098",
    "keterangan": "LULUS"
  },
  {
    "nama": "FAHRI ARDIANSYAH HARAHAP",
    "kelas": "IX - 5",
    "nisn": "0118028539",
    "keterangan": "LULUS"
  },
  {
    "nama": "FAJAR GLEN JHESON HAREFA",
    "kelas": "IX - 5",
    "nisn": "0099606336",
    "keterangan": "LULUS"
  },
  {
    "nama": "GHIFARI AZHAR NST",
    "kelas": "IX - 5",
    "nisn": "0107490001",
    "keterangan": "LULUS"
  },
  {
    "nama": "GILANG GUSTI PRADMUDYA",
    "kelas": "IX - 5",
    "nisn": "0109345080",
    "keterangan": "LULUS"
  },
  {
    "nama": "HAPPY SHAKILA",
    "kelas": "IX - 5",
    "nisn": "0103043286",
    "keterangan": "LULUS"
  },
  {
    "nama": "IRGI BAIM FAHREZI",
    "kelas": "IX - 5",
    "nisn": "0106238973",
    "keterangan": "LULUS"
  },
  {
    "nama": "KHAIRUNNISA SIMANUNGKALIT",
    "kelas": "IX - 5",
    "nisn": "0112030475",
    "keterangan": "LULUS"
  },
  {
    "nama": "KRISTIANI REJEKI SIMBOLON",
    "kelas": "IX - 5",
    "nisn": "0109755404",
    "keterangan": "LULUS"
  },
  {
    "nama": "M. AFANDI",
    "kelas": "IX - 5",
    "nisn": "0101057900",
    "keterangan": "LULUS"
  },
  {
    "nama": "MARCELLO AGUSTINO HUTASOIT",
    "kelas": "IX - 5",
    "nisn": "0101346859",
    "keterangan": "LULUS"
  },
  {
    "nama": "NAOMI EVITASARI SAGALA",
    "kelas": "IX - 5",
    "nisn": "0103821746",
    "keterangan": "LULUS"
  },
  {
    "nama": "NARA LIFA",
    "kelas": "IX - 5",
    "nisn": "0108411056",
    "keterangan": "LULUS"
  },
  {
    "nama": "NUR JANAH LAMEISYA",
    "kelas": "IX - 5",
    "nisn": "0107367763",
    "keterangan": "LULUS"
  },
  {
    "nama": "PERDIANSYAH PASARIBU",
    "kelas": "IX - 5",
    "nisn": "0108244088",
    "keterangan": "LULUS"
  },
  {
    "nama": "RAHAYU FEBRIAN LINTANG",
    "kelas": "IX - 5",
    "nisn": "0113324700",
    "keterangan": "LULUS"
  },
  {
    "nama": "RIFQI ANNA FI'I",
    "kelas": "IX - 5",
    "nisn": "0099230795",
    "keterangan": "LULUS"
  },
  {
    "nama": "RISCA ULINA SILALAHI",
    "kelas": "IX - 5",
    "nisn": "0101609021",
    "keterangan": "LULUS"
  },
  {
    "nama": "SEBASTIAN TIMOTI SIAHAAN",
    "kelas": "IX - 5",
    "nisn": "0106043269",
    "keterangan": "LULUS"
  },
  {
    "nama": "STEPHANIE LAURENSYA MANURUNG",
    "kelas": "IX - 5",
    "nisn": "0106441085",
    "keterangan": "LULUS"
  },
  {
    "nama": "TUTUR GITA SIMBOLON",
    "kelas": "IX - 5",
    "nisn": "0104268297",
    "keterangan": "LULUS"
  },
  {
    "nama": "WELL ALFREDO PAKPAHAN",
    "kelas": "IX - 5",
    "nisn": "0118920002",
    "keterangan": "LULUS"
  },
  {
    "nama": "YOHANNA VALEN SINAGA",
    "kelas": "IX - 5",
    "nisn": "0107348102",
    "keterangan": "LULUS"
  },
  {
    "nama": "YULI HANDAYANI",
    "kelas": "IX - 5",
    "nisn": "0091077351",
    "keterangan": "LULUS"
  },
  {
    "nama": "ANDREAS RIZKY JAYA SITANGGANG",
    "kelas": "IX - 6",
    "nisn": "0116021144",
    "keterangan": "LULUS"
  },
  {
    "nama": "AULIA SIDDIQ",
    "kelas": "IX - 6",
    "nisn": "0094711785",
    "keterangan": "LULUS"
  },
  {
    "nama": "CAHYA AUFA NIKEISHA",
    "kelas": "IX - 6",
    "nisn": "0102433506",
    "keterangan": "LULUS"
  },
  {
    "nama": "DENI ARYANTO HUTABARAT",
    "kelas": "IX - 6",
    "nisn": "0106935189",
    "keterangan": "LULUS"
  },
  {
    "nama": "DIANITA LUMBANGAOL",
    "kelas": "IX - 6",
    "nisn": "0106832089",
    "keterangan": "LULUS"
  },
  {
    "nama": "DINDA ALIFYA RAHMA",
    "kelas": "IX - 6",
    "nisn": "0103633452",
    "keterangan": "LULUS"
  },
  {
    "nama": "GRACE MANURUNG",
    "kelas": "IX - 6",
    "nisn": "0101249787",
    "keterangan": "LULUS"
  },
  {
    "nama": "HELDA SYAHVIRA",
    "kelas": "IX - 6",
    "nisn": "0105834030",
    "keterangan": "LULUS"
  },
  {
    "nama": "KHAISYAH RAMDHANI",
    "kelas": "IX - 6",
    "nisn": "0108322283",
    "keterangan": "LULUS"
  },
  {
    "nama": "MARIO FERRY SINAGA",
    "kelas": "IX - 6",
    "nisn": "0105001726",
    "keterangan": "LULUS"
  },
  {
    "nama": "MAUDI CAROLIN TATARANG",
    "kelas": "IX - 6",
    "nisn": "0109229477",
    "keterangan": "LULUS"
  },
  {
    "nama": "MUHAMMAD RAFA",
    "kelas": "IX - 6",
    "nisn": "0095900078",
    "keterangan": "LULUS"
  },
  {
    "nama": "NABILA AISYAH PUTRI",
    "kelas": "IX - 6",
    "nisn": 3101722219,
    "keterangan": "LULUS"
  },
  {
    "nama": "NANDAFA FAISRAWAN",
    "kelas": "IX - 6",
    "nisn": "0093508696",
    "keterangan": "LULUS"
  },
  {
    "nama": "NATALIA RUMIRIS NAINGGOLAN",
    "kelas": "IX - 6",
    "nisn": "0103401870",
    "keterangan": "LULUS"
  },
  {
    "nama": "NAYLA SAKINAH",
    "kelas": "IX - 6",
    "nisn": "0103016638",
    "keterangan": "LULUS"
  },
  {
    "nama": "PERDANA WAHYU SITANGGANG",
    "kelas": "IX - 6",
    "nisn": "0107813919",
    "keterangan": "LULUS"
  },
  {
    "nama": "RAHMIYANI",
    "kelas": "IX - 6",
    "nisn": 3091917496,
    "keterangan": "LULUS"
  },
  {
    "nama": "RAVAEL RE ANGLO GULTOM",
    "kelas": "IX - 6",
    "nisn": "0106791909",
    "keterangan": "LULUS"
  },
  {
    "nama": "RISHEL AURORA THERESIA MANIK",
    "kelas": "IX - 6",
    "nisn": "0104512362",
    "keterangan": "LULUS"
  },
  {
    "nama": "SALSABILA BATUBARA",
    "kelas": "IX - 6",
    "nisn": "0109753011",
    "keterangan": "LULUS"
  },
  {
    "nama": "STEVANIE MARIA SILITONGA",
    "kelas": "IX - 6",
    "nisn": "0102976476",
    "keterangan": "LULUS"
  },
  {
    "nama": "THRISNO TURNIP",
    "kelas": "IX - 6",
    "nisn": "0102751841",
    "keterangan": "LULUS"
  },
  {
    "nama": "TIMOTI JERIKO NABABAN",
    "kelas": "IX - 6",
    "nisn": "0107306941",
    "keterangan": "LULUS"
  },
  {
    "nama": "WAHYU ALFA RIZKY",
    "kelas": "IX - 6",
    "nisn": "0113740247",
    "keterangan": "LULUS"
  },
  {
    "nama": "YOLANDA ANGGRAINI SARAGIH",
    "kelas": "IX - 6",
    "nisn": "0104524335",
    "keterangan": "LULUS"
  },
  {
    "nama": "ZAHRA ARIFIN RAMBE",
    "kelas": "IX - 6",
    "nisn": "0103350288",
    "keterangan": "LULUS"
  },
  {
    "nama": "AKBAR FAUJAN GHANI",
    "kelas": "IX - 7",
    "nisn": "0096729284",
    "keterangan": "LULUS"
  },
  {
    "nama": "ANGEL AULIA SITANGGANG",
    "kelas": "IX - 7",
    "nisn": "0101684733",
    "keterangan": "LULUS"
  },
  {
    "nama": "ARLE SETIAWAN",
    "kelas": "IX - 7",
    "nisn": "0102342617",
    "keterangan": "LULUS"
  },
  {
    "nama": "BAGAS PRASETIYO",
    "kelas": "IX - 7",
    "nisn": "0108509311",
    "keterangan": "LULUS"
  },
  {
    "nama": "CHONYA SASMITA SARI",
    "kelas": "IX - 7",
    "nisn": "0091790658",
    "keterangan": "LULUS"
  },
  {
    "nama": "ELIA ROMAULI PASARIBU",
    "kelas": "IX - 7",
    "nisn": "0109401112",
    "keterangan": "LULUS"
  },
  {
    "nama": "FATUR RAHMAN",
    "kelas": "IX - 7",
    "nisn": "0103388741",
    "keterangan": "LULUS"
  },
  {
    "nama": "HAFIZ SANJAYA",
    "kelas": "IX - 7",
    "nisn": "0098136467",
    "keterangan": "LULUS"
  },
  {
    "nama": "IBRAHIM ARSYAVIN",
    "kelas": "IX - 7",
    "nisn": "0105591568",
    "keterangan": "LULUS"
  },
  {
    "nama": "JAMSEN ARLIANTA SEMBIRING",
    "kelas": "IX - 7",
    "nisn": "0109542815",
    "keterangan": "LULUS"
  },
  {
    "nama": "JESBERIKA NATASYA MANALU",
    "kelas": "IX - 7",
    "nisn": "0109650390",
    "keterangan": "LULUS"
  },
  {
    "nama": "KEVIN MAYDEN SIBARANI",
    "kelas": "IX - 7",
    "nisn": "0102094317",
    "keterangan": "LULUS"
  },
  {
    "nama": "KHOIRI RIZKI FATANULLAH",
    "kelas": "IX - 7",
    "nisn": "0091451424",
    "keterangan": "LULUS"
  },
  {
    "nama": "MALIKA AZKA",
    "kelas": "IX - 7",
    "nisn": "0102950588",
    "keterangan": "LULUS"
  },
  {
    "nama": "MECHY YOHANNA BR. LUMBAN GAOL",
    "kelas": "IX - 7",
    "nisn": "0105871531",
    "keterangan": "LULUS"
  },
  {
    "nama": "MUHAMMAD ARDIANSYAH",
    "kelas": "IX - 7",
    "nisn": "0108374848",
    "keterangan": "LULUS"
  },
  {
    "nama": "MUHAMMAD RAFA",
    "kelas": "IX - 7",
    "nisn": "0105692554",
    "keterangan": "LULUS"
  },
  {
    "nama": "NAZHILA KARENSA PUTRI",
    "kelas": "IX - 7",
    "nisn": "0103180885",
    "keterangan": "LULUS"
  },
  {
    "nama": "NOVRI AZI SYAHPUTRA",
    "kelas": "IX - 7",
    "nisn": "0091736582",
    "keterangan": "LULUS"
  },
  {
    "nama": "PASKHAS SUBANG",
    "kelas": "IX - 7",
    "nisn": "0091870850",
    "keterangan": "LULUS"
  },
  {
    "nama": "RACHEL CHERYL LETICIA HARAHAP",
    "kelas": "IX - 7",
    "nisn": "0106993251",
    "keterangan": "LULUS"
  },
  {
    "nama": "RARA NUR AZURA",
    "kelas": "IX - 7",
    "nisn": "0105292839",
    "keterangan": "LULUS"
  },
  {
    "nama": "RENALDI PURBA",
    "kelas": "IX - 7",
    "nisn": "0105020725",
    "keterangan": "LULUS"
  },
  {
    "nama": "SALWA APRILIANI BR.HARAHAP",
    "kelas": "IX - 7",
    "nisn": "0101048817",
    "keterangan": "LULUS"
  },
  {
    "nama": "SANTI KARTIKA SARI SIANTURI",
    "kelas": "IX - 7",
    "nisn": "0103904813",
    "keterangan": "LULUS"
  },
  {
    "nama": "SUKMA MULIA SARI BR SILALAHI",
    "kelas": "IX - 7",
    "nisn": "0105664741",
    "keterangan": "LULUS"
  },
  {
    "nama": "TIARA SARI DEWI",
    "kelas": "IX - 7",
    "nisn": "0094927813",
    "keterangan": "LULUS"
  },
  {
    "nama": "TIMBUL JAYA LIMBONG",
    "kelas": "IX - 7",
    "nisn": "0091397730",
    "keterangan": "LULUS"
  },
  {
    "nama": "TIMOTIUS JOSUA MANIK",
    "kelas": "IX - 7",
    "nisn": "0089540430",
    "keterangan": "LULUS"
  },
  {
    "nama": "WINDA LESTARI SIAGIAN",
    "kelas": "IX - 7",
    "nisn": "0109604539",
    "keterangan": "LULUS"
  },
  {
    "nama": "YOSI OKTAVIA SIMAMORA",
    "kelas": "IX - 7",
    "nisn": "0095838861",
    "keterangan": "LULUS"
  },
  {
    "nama": "ZALSA AMANDA SABILAH",
    "kelas": "IX - 7",
    "nisn": "0102948362",
    "keterangan": "LULUS"
  },
  {
    "nama": "AGATA LASRIA PARSAULIAN SIHOMBING",
    "kelas": "IX - 8",
    "nisn": "0101503046",
    "keterangan": "LULUS"
  },
  {
    "nama": "AKMAL HASSAN NASUTION",
    "kelas": "IX - 8",
    "nisn": "0109514579",
    "keterangan": "LULUS"
  },
  {
    "nama": "ANDIKA PRASETIO",
    "kelas": "IX - 8",
    "nisn": "0091045303",
    "keterangan": "LULUS"
  },
  {
    "nama": "ASTRI OKTAVIANI SINAMBELA",
    "kelas": "IX - 8",
    "nisn": "0109567700",
    "keterangan": "LULUS"
  },
  {
    "nama": "BIMA PUTRA TRISANTOSO",
    "kelas": "IX - 8",
    "nisn": "0109990756",
    "keterangan": "LULUS"
  },
  {
    "nama": "DAMAR PAMUJI",
    "kelas": "IX - 8",
    "nisn": "0108580176",
    "keterangan": "LULUS"
  },
  {
    "nama": "DEWI SINTA",
    "kelas": "IX - 8",
    "nisn": "0095872732",
    "keterangan": "LULUS"
  },
  {
    "nama": "DIANGGA TRI LESMANA",
    "kelas": "IX - 8",
    "nisn": "0094357720",
    "keterangan": "LULUS"
  },
  {
    "nama": "ELVINA FLORENCE SIMANJUNTAK",
    "kelas": "IX - 8",
    "nisn": "0105183438",
    "keterangan": "LULUS"
  },
  {
    "nama": "HAFIZ PRATAMA",
    "kelas": "IX - 8",
    "nisn": "0103912614",
    "keterangan": "LULUS"
  },
  {
    "nama": "HARITH HAZIQ HARAHAP",
    "kelas": "IX - 8",
    "nisn": "0102122554",
    "keterangan": "LULUS"
  },
  {
    "nama": "INDA DEFA KIRANA",
    "kelas": "IX - 8",
    "nisn": "0103575122",
    "keterangan": "LULUS"
  },
  {
    "nama": "JESICHA ANJANI SINAGA",
    "kelas": "IX - 8",
    "nisn": "0107709253",
    "keterangan": "LULUS"
  },
  {
    "nama": "KEVIN LUMBAN TOBING",
    "kelas": "IX - 8",
    "nisn": "0113155777",
    "keterangan": "LULUS"
  },
  {
    "nama": "KRISTIAN MORALES HALOMOAN SINAGA",
    "kelas": "IX - 8",
    "nisn": "0096793878",
    "keterangan": "LULUS"
  },
  {
    "nama": "LUFFI FATUROZAQ",
    "kelas": "IX - 8",
    "nisn": "0109105862",
    "keterangan": "LULUS"
  },
  {
    "nama": "MAKMUR RIZKY",
    "kelas": "IX - 8",
    "nisn": "0106501336",
    "keterangan": "LULUS"
  },
  {
    "nama": "MAULANA AJA JAYA",
    "kelas": "IX - 8",
    "nisn": "0104006221",
    "keterangan": "LULUS"
  },
  {
    "nama": "MELATI INDAH S  NABABAN",
    "kelas": "IX - 8",
    "nisn": "0103627750",
    "keterangan": "LULUS"
  },
  {
    "nama": "NAZWA ALFIRA",
    "kelas": "IX - 8",
    "nisn": "0106717250",
    "keterangan": "LULUS"
  },
  {
    "nama": "PUTRI SAPITRI",
    "kelas": "IX - 8",
    "nisn": "0101252434",
    "keterangan": "LULUS"
  },
  {
    "nama": "RAHEL MONICA TAMPUBOLON",
    "kelas": "IX - 8",
    "nisn": "0106678760",
    "keterangan": "LULUS"
  },
  {
    "nama": "RISKI HABIBI",
    "kelas": "IX - 8",
    "nisn": "0103218702",
    "keterangan": "LULUS"
  },
  {
    "nama": "SAMUEL RISKI PANJAITAN",
    "kelas": "IX - 8",
    "nisn": "0101133792",
    "keterangan": "LULUS"
  },
  {
    "nama": "SARA AMELLIA",
    "kelas": "IX - 8",
    "nisn": "0086184114",
    "keterangan": "LULUS"
  },
  {
    "nama": "STEFANI NURCAHAYA SITUMORANG",
    "kelas": "IX - 8",
    "nisn": "0117427406",
    "keterangan": "LULUS"
  },
  {
    "nama": "SYALOMITA VALEN MARISA",
    "kelas": "IX - 8",
    "nisn": "0103193862",
    "keterangan": "LULUS"
  },
  {
    "nama": "SYIFA INAYAH LUBIS",
    "kelas": "IX - 8",
    "nisn": "0099871452",
    "keterangan": "LULUS"
  },
  {
    "nama": "WIDI TRI BINTANG SARAGI",
    "kelas": "IX - 8",
    "nisn": "0117605488",
    "keterangan": "LULUS"
  },
  {
    "nama": "WINONA MARGARETHA HUTABARAT",
    "kelas": "IX - 8",
    "nisn": "0106984464",
    "keterangan": "LULUS"
  },
  {
    "nama": "ZIFANNI AULIA",
    "kelas": "IX - 8",
    "nisn": "0102582416",
    "keterangan": "LULUS"
  }
]